ospeech/__init__.py
ospeech/__main__.py
ospeech/gradio_ui.py
ospeech/models.py
ospeech/values.py
ospeech/inference/__init__.py
ospeech/text/__init__.py
ospeech/text/normalization.py
ospeech/text/symbols.py
ospeech/text/tokenizers.py
ospeech-1.4.0.dist-info/METADATA
ospeech-1.4.0.dist-info/WHEEL
ospeech-1.4.0.dist-info/entry_points.txt
ospeech-1.4.0.dist-info/licenses/LICENSE
ospeech-1.4.0.dist-info/RECORD
