Metadata-Version: 2.3
Name: ospeech
Version: 1.4.0
Summary: Minimum dependency inference library for OptiSpeech TTS models
Author-email: mush42 <ibnomer2011@hotmail.com>
License-File: LICENSE
Requires-Python: >=3.10
Requires-Dist: mureq>=0.2.0
Requires-Dist: numpy<2.0.0
Requires-Dist: onnxruntime>=1.19.2
Requires-Dist: soundfile>=0.12.1
Requires-Dist: tqdm>=4.66.5
Provides-Extra: espeak
Requires-Dist: piper-phonemize>=1.1.0; extra == 'espeak'
Provides-Extra: gradio
Requires-Dist: gradio>=4.42.0; extra == 'gradio'
